puzzle_game-0.1.0.dist-info/licenses/LICENSE
puzzle_gameshaima/__init__.py
puzzle_gameshaima/game.py
puzzle_gameshaima/setup.py
puzzle_game-0.1.0.dist-info/METADATA
puzzle_game-0.1.0.dist-info/WHEEL
puzzle_game-0.1.0.dist-info/top_level.txt
puzzle_game-0.1.0.dist-info/RECORD
