Metadata-Version: 2.4
Name: puzzle-game
Version: 0.1.0
Summary: 8-puzzle solver using BFS
Author-email: "en.shaima" <shaimamanager3@example.com>
License: MIT
Requires-Python: >=3.7
License-File: LICENSE
Dynamic: license-file
